LICENSE
MANIFEST.in
README.rst
setup.py
django_recaptcha_mailhide.egg-info/PKG-INFO
django_recaptcha_mailhide.egg-info/SOURCES.txt
django_recaptcha_mailhide.egg-info/dependency_links.txt
django_recaptcha_mailhide.egg-info/requires.txt
django_recaptcha_mailhide.egg-info/top_level.txt
recaptcha_mailhide/__init__.py
recaptcha_mailhide/locale/.DS_Store
recaptcha_mailhide/locale/pl_PL/.DS_Store
recaptcha_mailhide/locale/pl_PL/LC_MESSAGES/django.po
recaptcha_mailhide/templates/.DS_Store
recaptcha_mailhide/templates/mailhide/email.html
recaptcha_mailhide/templatetags/.DS_Store
recaptcha_mailhide/templatetags/__init__.py
recaptcha_mailhide/templatetags/mailhide.py